attachments/__init__.py
attachments/adapt.py
attachments/cli.py
attachments/config.py
attachments/core.py
attachments/dsl_info.py
attachments/dsl_suggestion.py
attachments/dspy.py
attachments/highest_level_api.py
attachments/load.py
attachments/matchers.py
attachments/modify.py
attachments/present.py
attachments/py.typed
attachments/refine.py
attachments/split.py
attachments/data/__init__.py
attachments/loaders/__init__.py
attachments/loaders/data/__init__.py
attachments/loaders/data/csv.py
attachments/loaders/documents/__init__.py
attachments/loaders/documents/office.py
attachments/loaders/documents/pdf.py
attachments/loaders/documents/text.py
attachments/loaders/media/__init__.py
attachments/loaders/media/archives.py
attachments/loaders/media/images.py
attachments/loaders/media/vector_graphics.py
attachments/loaders/repositories/__init__.py
attachments/loaders/repositories/directories.py
attachments/loaders/repositories/git.py
attachments/loaders/repositories/utils.py
attachments/loaders/web/__init__.py
attachments/loaders/web/urls.py
attachments/pipelines/__init__.py
attachments/pipelines/code_processor.py
attachments/pipelines/csv_processor.py
attachments/pipelines/docx_processor.py
attachments/pipelines/example_processors.py
attachments/pipelines/excel_processor.py
attachments/pipelines/image_processor.py
attachments/pipelines/ipynb_processor.py
attachments/pipelines/pdf_processor.py
attachments/pipelines/pptx_processor.py
attachments/pipelines/report_processor.py
attachments/pipelines/vector_graphics_processor.py
attachments/pipelines/webpage_processor.py
attachments/presenters/__init__.py
attachments/presenters/data/__init__.py
attachments/presenters/data/repositories.py
attachments/presenters/data/summaries.py
attachments/presenters/metadata/__init__.py
attachments/presenters/metadata/info.py
attachments/presenters/text/__init__.py
attachments/presenters/text/markdown.py
attachments/presenters/text/plain.py
attachments/presenters/text/structured.py
attachments-0.25.1.dist-info/licenses/LICENSE
attachments-0.25.1.dist-info/METADATA
attachments-0.25.1.dist-info/WHEEL
attachments-0.25.1.dist-info/entry_points.txt
attachments-0.25.1.dist-info/top_level.txt
attachments-0.25.1.dist-info/RECORD
