Metadata-Version: 2.4
Name: attachments
Version: 0.25.1
Summary: The Python funnel for LLM context - turn any file into model-ready text + images, in one line.
Author-email: Maxime Rivest <mrive052@gmail.com>
License-Expression: MIT
Project-URL: Homepage, https://maximerivest.github.io/attachments/
Project-URL: Documentation, https://maximerivest.github.io/attachments/
Project-URL: Repository, https://github.com/maximerivest/attachments
Project-URL: Bug Tracker, https://github.com/maximerivest/attachments/issues
Project-URL: Changelog, https://maximerivest.github.io/attachments/changelog.html
Keywords: llm,ai,pdf,document,multimodal,openai,claude,context,attachments
Classifier: Development Status :: 4 - Beta
Classifier: Intended Audience :: Developers
Classifier: Intended Audience :: Science/Research
Classifier: Operating System :: OS Independent
Classifier: Programming Language :: Python :: 3
Classifier: Programming Language :: Python :: 3.10
Classifier: Programming Language :: Python :: 3.11
Classifier: Programming Language :: Python :: 3.12
Classifier: Topic :: Scientific/Engineering :: Artificial Intelligence
Classifier: Topic :: Software Development :: Libraries :: Python Modules
Classifier: Topic :: Text Processing
Classifier: Topic :: Multimedia
Requires-Python: >=3.10
License-File: LICENSE
Requires-Dist: requests>=2.25.0
Requires-Dist: beautifulsoup4>=4.9.0
Requires-Dist: pillow>=11.2.1
Requires-Dist: pydantic>=2.11.5
Requires-Dist: pdfplumber>=0.11.6
Requires-Dist: pillow-heif>=0.22.0
Requires-Dist: nbformat>=5.10.4
Requires-Dist: copykitten>=1.2.2
Requires-Dist: typer>=0.12
Requires-Dist: pyperclip>=1.8
Requires-Dist: pytesseract>=0.3.13
Requires-Dist: pypdfium2>=4.30.0
Provides-Extra: dev
Requires-Dist: pytest>=8.0.0; extra == "dev"
Requires-Dist: pytest-randomly>=3.15.0; extra == "dev"
Requires-Dist: pytest-cov>=4.0.0; extra == "dev"
Requires-Dist: black>=24.0.0; extra == "dev"
Requires-Dist: ruff>=0.5.6; extra == "dev"
Requires-Dist: mypy>=1.8.0; extra == "dev"
Requires-Dist: pre-commit>=3.6.0; extra == "dev"
Requires-Dist: mystmd>=1.2.0; extra == "dev"
Requires-Dist: jupyter>=1.0.0; extra == "dev"
Requires-Dist: jupytext>=1.16.0; extra == "dev"
Requires-Dist: sphinx>=7.0.0; extra == "dev"
Requires-Dist: sphinx-autodoc2>=0.5.0; extra == "dev"
Requires-Dist: ipykernel>=6.29.5; extra == "dev"
Requires-Dist: dspy-ai>=2.6.24; extra == "dev"
Requires-Dist: python-pptx>=1.0.2; extra == "dev"
Provides-Extra: common
Requires-Dist: pandas>=2.0.0; extra == "common"
Requires-Dist: Pillow>=10.0.0; extra == "common"
Requires-Dist: pdfplumber>=0.10.0; extra == "common"
Requires-Dist: python-pptx>=1.0.2; extra == "common"
Requires-Dist: python-docx>=1.1.0; extra == "common"
Requires-Dist: openpyxl>=3.1.0; extra == "common"
Requires-Dist: pypdfium2>=4.0.0; extra == "common"
Provides-Extra: office
Requires-Dist: python-pptx>=0.6.0; extra == "office"
Requires-Dist: python-docx>=1.1.0; extra == "office"
Requires-Dist: openpyxl>=3.1.0; extra == "office"
Provides-Extra: 3d
Requires-Dist: bpy>=4.4.0; (python_version >= "3.11" and python_version < "3.12") and extra == "3d"
Requires-Dist: trimesh>=4.3.0; extra == "3d"
Requires-Dist: pyrender>=0.1.45; extra == "3d"
Requires-Dist: numpy>=1.24.0; extra == "3d"
Provides-Extra: pdf
Requires-Dist: pdfplumber>=0.7.0; extra == "pdf"
Requires-Dist: pypdf>=5.0.0; extra == "pdf"
Requires-Dist: pypdfium2>=4.26.0; extra == "pdf"
Provides-Extra: extended
Requires-Dist: pillow-heif>=0.22.0; extra == "extended"
Requires-Dist: pytesseract>=0.3.10; extra == "extended"
Requires-Dist: copykitten>=1.0.0; extra == "extended"
Provides-Extra: browser
Requires-Dist: playwright>=1.43.0; extra == "browser"
Provides-Extra: most
Requires-Dist: dspy-ai>=2.6.24; extra == "most"
Requires-Dist: pandas>=1.3.0; extra == "most"
Requires-Dist: Pillow>=8.0.0; extra == "most"
Requires-Dist: pdfplumber>=0.7.0; extra == "most"
Requires-Dist: python-pptx>=0.6.21; extra == "most"
Requires-Dist: python-docx>=0.8.11; extra == "most"
Requires-Dist: openpyxl>=3.0.9; extra == "most"
Requires-Dist: pillow-heif>=0.22.0; extra == "most"
Requires-Dist: pytesseract>=0.3.10; extra == "most"
Requires-Dist: copykitten>=1.0.0; extra == "most"
Requires-Dist: pypdf>=5.0.0; extra == "most"
Requires-Dist: pypdfium2>=4.26.0; extra == "most"
Requires-Dist: playwright>=1.43.0; extra == "most"
Requires-Dist: trimesh>=4.3.0; extra == "most"
Requires-Dist: pyrender>=0.1.45; extra == "most"
Provides-Extra: test
Requires-Dist: pytest>=8.0.0; extra == "test"
Requires-Dist: pytest-randomly>=3.15.0; extra == "test"
Requires-Dist: pytest-cov>=4.0.0; extra == "test"
Requires-Dist: tox>=4.0.0; extra == "test"
Requires-Dist: coverage[toml]>=7.4.0; extra == "test"
Dynamic: license-file
